SteamCharts.py
SteamPlayerCharts-0.2.1.dist-info/METADATA
SteamPlayerCharts-0.2.1.dist-info/WHEEL
SteamPlayerCharts-0.2.1.dist-info/top_level.txt
SteamPlayerCharts-0.2.1.dist-info/RECORD
