Metadata-Version: 2.1
Name: SteamPlayerCharts
Version: 0.2.1
Summary: A Python wrapper for SteamCharts
Author: Serpensin
Requires-Dist: aiohttp
Requires-Dist: beautifulsoup4
